drf_firebase_auth_cavoke/__init__.py
drf_firebase_auth_cavoke/apps.py
drf_firebase_auth_cavoke/authentication.py
drf_firebase_auth_cavoke/models.py
drf_firebase_auth_cavoke/settings.py
drf_firebase_auth_cavoke/migrations/0001_initial.py
drf_firebase_auth_cavoke/migrations/__init__.py
drf_firebase_auth_cavoke-0.0.7.dist-info/METADATA
drf_firebase_auth_cavoke-0.0.7.dist-info/WHEEL
drf_firebase_auth_cavoke-0.0.7.dist-info/top_level.txt
drf_firebase_auth_cavoke-0.0.7.dist-info/RECORD
