Metadata-Version: 2.1
Name: drf-firebase-auth-cavoke
Version: 0.0.7
Summary: Custom DRF authentication backend.
Home-page: https://github.com/cavoke-project/drf-firebase-auth-cavoke
Author: Alex Kovrigin
Author-email: a.kovrigin0@gmail.com
License: MIT
Platform: UNKNOWN
Classifier: Development Status :: 5 - Production/Stable
Classifier: Environment :: Web Environment
Classifier: Framework :: Django
Classifier: Intended Audience :: Developers
Classifier: License :: OSI Approved :: MIT License
Classifier: Operating System :: OS Independent
Classifier: Programming Language :: Python
Classifier: Programming Language :: Python :: 3
Classifier: Programming Language :: Python :: 3.3
Classifier: Programming Language :: Python :: 3.4
Classifier: Programming Language :: Python :: 3.5
Classifier: Programming Language :: Python :: 3.6
Classifier: Topic :: Internet :: WWW/HTTP
Requires-Dist: firebase-admin (>=2.0.0)
